math_lib/example.cc
math_lib/example.cpython-39-x86_64-linux-gnu.so
math_lib/exmaple.py
math_lib/test1.py
water_lyf-2.0.0.dist-info/LICENSE
water_lyf-2.0.0.dist-info/METADATA
water_lyf-2.0.0.dist-info/WHEEL
water_lyf-2.0.0.dist-info/top_level.txt
water_lyf-2.0.0.dist-info/RECORD
