Metadata-Version: 2.1
Name: water-lyf
Version: 2.0.0
Summary: This is description
Home-page: https://github.com/pypa/sampleproject
Download-URL: https://github.com/pypa/sampleproject
Author: Yifan
Author-email: liyifan1004@qq.com
License: Apache 2.0
Project-URL: Bug Tracker, https://github.com/pypa/sampleproject/issues
Project-URL: Documentation, https://github.com/pypa/sampleproject/issues
Classifier: Development Status :: 5 - Production/Stable
Classifier: Intended Audience :: Developers
Classifier: Intended Audience :: Education
Classifier: Intended Audience :: Science/Research
Classifier: License :: OSI Approved :: Apache Software License
Classifier: Programming Language :: Python :: 3.7
Classifier: Programming Language :: Python :: 3.8
Classifier: Programming Language :: Python :: 3.9
Classifier: Programming Language :: Python :: 3.10
Classifier: Topic :: Scientific/Engineering
Classifier: Topic :: Scientific/Engineering :: Mathematics
Classifier: Topic :: Scientific/Engineering :: Artificial Intelligence
Classifier: Topic :: Software Development
Classifier: Topic :: Software Development :: Libraries
Classifier: Topic :: Software Development :: Libraries :: Python Modules
Requires-Python: >=3.7, <=3.10
License-File: LICENSE
